databas3/__init__.py
databas3/main.py
database/__init__.py
database/main.py
databas3-0.0.0.dist-info/LICENSE
databas3-0.0.0.dist-info/METADATA
databas3-0.0.0.dist-info/WHEEL
databas3-0.0.0.dist-info/top_level.txt
databas3-0.0.0.dist-info/RECORD
