Metadata-Version: 2.1
Name: databas3
Version: 0.0.0
Summary: Terminal UI application that allows you to manage your database! :tada:
Home-page: https://github.com/Kludex/databas3
Author: Marcelo Trylesinski
Author-email: marcelotryle@gmail.com
License: MIT
Platform: UNKNOWN
Classifier: License :: OSI Approved :: MIT License
Classifier: Programming Language :: Python :: 3
Classifier: Programming Language :: Python :: 3 :: Only
Classifier: Programming Language :: Python :: 3.8
Classifier: Programming Language :: Python :: 3.9
Classifier: Programming Language :: Python :: 3.10
Classifier: Programming Language :: Python :: Implementation :: CPython
Requires-Python: >=3.8.0
License-File: LICENSE
Requires-Dist: textual (>=0.1.12)
